rayvision_clarisse/__init__.py
rayvision_clarisse/analyse_clarisse.py
rayvision_clarisse/constants.py
rayvision_clarisse/utils.py
rayvision_clarisse/tests/__init__.py
rayvision_clarisse/tests/conftest.py
rayvision_clarisse/tests/test_analyse.py
rayvision_clarisse/tests/test_utils.py
rayvision_clarisse/tool/py2/Analyze.exe
rayvision_clarisse/tool/py2/python27.dll
rayvision_clarisse/tool/py2/python27.zip
rayvision_clarisse/tool/py3/Analyze.exe
rayvision_clarisse/tool/py3/python34.dll
rayvision_clarisse/tool/py3/python34.zip
rayvision_clarisse-1.3.3.dist-info/METADATA
rayvision_clarisse-1.3.3.dist-info/WHEEL
rayvision_clarisse-1.3.3.dist-info/top_level.txt
rayvision_clarisse-1.3.3.dist-info/RECORD
